MANIFEST.in
setup.py
neorg/__init__.py
neorg/commands.py
neorg/config.py
neorg/data.py
neorg/schema.sql
neorg/search.py
neorg/verutils.py
neorg/web.py
neorg/wiki.py
neorg.egg-info/PKG-INFO
neorg.egg-info/SOURCES.txt
neorg.egg-info/dependency_links.txt
neorg.egg-info/entry_points.txt
neorg.egg-info/requires.txt
neorg.egg-info/top_level.txt
neorg/static/favicon.ico
neorg/static/html4css1.css
neorg/static/style.css
neorg/static/help/changelog.html
neorg/static/help/commands.html
neorg/static/help/examples.html
neorg/static/help/genindex.html
neorg/static/help/index.html
neorg/static/help/objects.inv
neorg/static/help/search.html
neorg/static/help/searchindex.js
neorg/static/help/_sources/changelog.txt
neorg/static/help/_sources/commands.txt
neorg/static/help/_sources/examples.txt
neorg/static/help/_sources/index.txt
neorg/static/help/_static/alert_info_32.png
neorg/static/help/_static/alert_warning_32.png
neorg/static/help/_static/basic.css
neorg/static/help/_static/bg-page.png
neorg/static/help/_static/bullet_orange.png
neorg/static/help/_static/doctools.js
neorg/static/help/_static/file.png
neorg/static/help/_static/haiku.css
neorg/static/help/_static/jquery.js
neorg/static/help/_static/minus.png
neorg/static/help/_static/plus.png
neorg/static/help/_static/pygments.css
neorg/static/help/_static/searchtools.js
neorg/static/help/_static/underscore.js
neorg/templates/confirm_delete.html
neorg/templates/descendants.html
neorg/templates/edit.html
neorg/templates/history.html
neorg/templates/layout.html
neorg/templates/page.html
neorg/templates/preview.html
neorg/templates/search.html
neorg/tests/__init__.py
neorg/tests/test_data.py
neorg/tests/test_verutils.py
neorg/tests/test_web.py
neorg/tests/test_wiki.py
neorg/tests/utils.py
neorg/tests/texts/00_replacement_text.txt
neorg/tests/texts/demo.txt