Metadata-Version: 1.0
Name: neorg
Version: 0.0.3
Summary: NEOrg - Numerical Experiment Organizer
Home-page: https://bitbucket.org/tkf/neorg
Author: Takafumi Arakaki
Author-email: aka.tkf@gmail.com
License: MIT License
Keywords: numerical simulation,research
Platform: UNKNOWN
Classifier: Development Status :: 3 - Alpha
Classifier: Intended Audience :: Science/Research
Classifier: Operating System :: POSIX :: Linux
Classifier: License :: OSI Approved :: MIT License
Classifier: Programming Language :: Python
Classifier: Topic :: Scientific/Engineering
